{
  "columns": {
    "neu": {
      "name": "Neu",
      "items": [
        {
          "id": "gn7do1q9",
          "content": "Straßenreinigung",
          "createdAt": "2025-10-17T19:02:15.905Z",
          "statusSince": "2025-10-17T19:02:15.905Z",
          "assignedVehicles": [],
          "everVehicles": [],
          "everPersonnel": 0,
          "ort": "Unterrain\nUnterrain - Feldkirchen in Kärnten",
          "typ": "T0, Straßenreinigung",
          "externalId": "23885621",
          "alerted": "FF Waiern",
          "latitude": 46.7148242727,
          "longitude": 14.0878256873,
          "location": "",
          "timestamp": "2025-10-16T07:38:39.000Z",
          "description": ""
        }
      ]
    },
    "in-bearbeitung": {
      "name": "In Bearbeitung",
      "items": [
        {
          "id": "ghahbzxs",
          "content": "Brand",
          "createdAt": "2025-10-17T18:58:55.082Z",
          "statusSince": "2025-10-17T19:01:24.599Z",
          "assignedVehicles": [
            "X4ro9wm"
          ],
          "everVehicles": [
            "X4ro9wm",
            "X9rxuel"
          ],
          "everPersonnel": 9,
          "ort": "Lannerweg, 8071 Hausmannstätten, Österreich",
          "typ": "Brand",
          "externalId": "",
          "alerted": "",
          "latitude": 46.9932567,
          "longitude": 15.5078872,
          "location": "",
          "description": "",
          "timestamp": null,
          "manualPersonnel": 1
        }
      ]
    },
    "erledigt": {
      "name": "Erledigt",
      "items": []
    }
  }
}